electionbuddy_python/__about__.py
electionbuddy_python/__init__.py
electionbuddy_python-0.0.1.dist-info/METADATA
electionbuddy_python-0.0.1.dist-info/WHEEL
electionbuddy_python-0.0.1.dist-info/licenses/LICENSE.txt
electionbuddy_python-0.0.1.dist-info/RECORD
